aiosmtpd/__init__.py
aiosmtpd/__main__.py
aiosmtpd/controller.py
aiosmtpd/handlers.py
aiosmtpd/lmtp.py
aiosmtpd/main.py
aiosmtpd/proxy_protocol.py
aiosmtpd/py.typed
aiosmtpd/smtp.py
aiosmtpd/docs/.gitignore
aiosmtpd/docs/Makefile
aiosmtpd/docs/NEWS.rst
aiosmtpd/docs/RTD-requirements.txt
aiosmtpd/docs/__init__.py
aiosmtpd/docs/auth.rst
aiosmtpd/docs/cli.rst
aiosmtpd/docs/concepts.rst
aiosmtpd/docs/conf.py
aiosmtpd/docs/controller.rst
aiosmtpd/docs/handlers.rst
aiosmtpd/docs/index.rst
aiosmtpd/docs/intro.rst
aiosmtpd/docs/lmtp.rst
aiosmtpd/docs/manpage.rst
aiosmtpd/docs/migrating.rst
aiosmtpd/docs/proxyprotocol.rst
aiosmtpd/docs/smtp.rst
aiosmtpd/docs/testing.rst
aiosmtpd/docs/_exts/autoprogramm.py
aiosmtpd/docs/_static/aiosmtpd.css
aiosmtpd/qa/__init__.py
aiosmtpd/qa/test_0packaging.py
aiosmtpd/qa/test_1testsuite.py
aiosmtpd/testing/__init__.py
aiosmtpd/testing/helpers.py
aiosmtpd/testing/statuscodes.py
aiosmtpd/tests/__init__.py
aiosmtpd/tests/conftest.py
aiosmtpd/tests/test_handlers.py
aiosmtpd/tests/test_lmtp.py
aiosmtpd/tests/test_main.py
aiosmtpd/tests/test_misc.py
aiosmtpd/tests/test_proxyprotocol.py
aiosmtpd/tests/test_server.py
aiosmtpd/tests/test_smtp.py
aiosmtpd/tests/test_smtps.py
aiosmtpd/tests/test_starttls.py
aiosmtpd/tests/certs/__init__.py
aiosmtpd/tests/certs/server.crt
aiosmtpd/tests/certs/server.key
aiosmtpd/tests/certs/server_alt.crt
aiosmtpd/tests/certs/server_alt.key
aiosmtpd-1.4.4.post2.dist-info/LICENSE
aiosmtpd-1.4.4.post2.dist-info/METADATA
aiosmtpd-1.4.4.post2.dist-info/NOTICE
aiosmtpd-1.4.4.post2.dist-info/WHEEL
aiosmtpd-1.4.4.post2.dist-info/entry_points.txt
aiosmtpd-1.4.4.post2.dist-info/top_level.txt
aiosmtpd-1.4.4.post2.dist-info/RECORD
