Metadata-Version: 2.1
Name: aiosmtpd
Version: 1.4.4.post2
Summary: aiosmtpd - asyncio based SMTP server
Home-page: https://aiosmtpd.readthedocs.io/
Maintainer: The aiosmtpd Developers
Maintainer-email: aiosmtpd@googlegroups.com
License: Apache-2.0
Project-URL: Bug Tracker, https://github.com/aio-libs/aiosmtpd/issues
Project-URL: Documentation, https://aiosmtpd.readthedocs.io/
Project-URL: Source Code, https://github.com/aio-libs/aiosmtpd
Keywords: email,smtpd,smtp
Classifier: License :: OSI Approved
Classifier: License :: OSI Approved :: Apache Software License
Classifier: Intended Audience :: Developers
Classifier: Operating System :: Microsoft :: Windows
Classifier: Operating System :: POSIX :: BSD :: FreeBSD
Classifier: Operating System :: POSIX :: Linux
Classifier: Programming Language :: Python :: 3 :: Only
Classifier: Programming Language :: Python :: 3.7
Classifier: Programming Language :: Python :: 3.8
Classifier: Programming Language :: Python :: 3.9
Classifier: Programming Language :: Python :: 3.10
Classifier: Programming Language :: Python :: 3.11
Classifier: Programming Language :: Python :: Implementation :: CPython
Classifier: Programming Language :: Python :: Implementation :: PyPy
Classifier: Topic :: Communications :: Email :: Mail Transport Agents
Classifier: Framework :: AsyncIO
Requires-Python: ~=3.7
License-File: LICENSE
License-File: NOTICE
